nimmunize/__init__.py
nimmunize/_version.py
nimmunize/catchup.py
nimmunize/cli.py
nimmunize/schedule.py
nimmunize/survey.py
nimmunize/data/nphcda_schedule.json
nimmunize-1.0.4.dist-info/licenses/LICENSE
nimmunize-1.0.4.dist-info/METADATA
nimmunize-1.0.4.dist-info/WHEEL
nimmunize-1.0.4.dist-info/top_level.txt
nimmunize-1.0.4.dist-info/RECORD
