Metadata-Version: 2.4
Name: nimmunize
Version: 1.0.4
Summary: Nigeria immunisation scheduling & survey analytics package
Author-email: "Daniel T. Omole" <topeomole55@gmail.com>
License-Expression: GPL-3.0-or-later
Project-URL: Homepage, https://github.com/Nerdthink/nimmunize
Project-URL: Source, https://github.com/Nerdthink/nimmunize
Project-URL: Issues, https://github.com/Nerdthink/nimmunize/issues
Project-URL: Documentation, https://nimmunize.readthedocs.io
Requires-Python: >=3.9
License-File: LICENSE
Requires-Dist: pandas>=2
Requires-Dist: click>=8
Requires-Dist: python-dateutil
Dynamic: license-file
